cdk_ssm_parameter_store/__init__.py
cdk_ssm_parameter_store/py.typed
cdk_ssm_parameter_store/_jsii/__init__.py
cdk_ssm_parameter_store/_jsii/cdk-ssm-parameter-store@0.1.91.jsii.tgz
cdk_ssm_parameter_store-0.1.91.dist-info/LICENSE
cdk_ssm_parameter_store-0.1.91.dist-info/METADATA
cdk_ssm_parameter_store-0.1.91.dist-info/WHEEL
cdk_ssm_parameter_store-0.1.91.dist-info/top_level.txt
cdk_ssm_parameter_store-0.1.91.dist-info/RECORD
